mylib/HSJlibrary.py
HSJLib-0.0.1.dist-info/METADATA
HSJLib-0.0.1.dist-info/WHEEL
HSJLib-0.0.1.dist-info/top_level.txt
HSJLib-0.0.1.dist-info/RECORD
