Metadata-Version: 2.1
Name: HSJLib
Version: 0.0.1
Summary: HSJ's library
Home-page: https://github.com/HSJoss/my-oss
Download-URL: https://github.com/HSJoss/my-oss/
Author: HSJ
Classifier: Programming Language :: Python :: 3
